world_wall_clock/__init__.py
world_wall_clock/__main__.py
world_wall_clock/wwclock.py
world_wall_clock-0.1.5.dist-info/COPYING.md
world_wall_clock-0.1.5.dist-info/METADATA
world_wall_clock-0.1.5.dist-info/WHEEL
world_wall_clock-0.1.5.dist-info/entry_points.txt
world_wall_clock-0.1.5.dist-info/RECORD
