Metadata-Version: 2.3
Name: world-wall-clock
Version: 0.1.5
Summary: TUI world clock application
License: GPL-3.0-or-later
Author: Dominic Delabruere
Author-email: dominic.delabruere@gmail.com
Requires-Python: >=3.10,<4.0
Classifier: License :: OSI Approved :: GNU General Public License v3 or later (GPLv3+)
Classifier: Programming Language :: Python :: 3
Classifier: Programming Language :: Python :: 3.10
Classifier: Programming Language :: Python :: 3.11
Classifier: Programming Language :: Python :: 3.12
Classifier: Programming Language :: Python :: 3.13
Requires-Dist: tzdata (>=2023.3)
Requires-Dist: urwid (>=2.2.2,<3.0.0)
Requires-Dist: xdg-base-dirs (>=6.0.1,<7.0.0)
Project-URL: Repository, https://github.com/ddelabru/world-wall-clock
